forklift
tests
