Metadata-Version: 1.0
Name: docker-forklift
Version: 0.2.41
Summary: Utility for running a container
Home-page: https://github.com/infoxchange/docker-forklift
Author: Infoxchange Australia development team
Author-email: devs@infoxchange.net.au
License: Apache 2.0
Platform: UNKNOWN
